setup.py
livepandas/__init__.py
livepandas/cli.py
livepandas/server.py
livepandas.egg-info/PKG-INFO
livepandas.egg-info/SOURCES.txt
livepandas.egg-info/dependency_links.txt
livepandas.egg-info/entry_points.txt
livepandas.egg-info/requires.txt
livepandas.egg-info/top_level.txt