Metadata-Version: 1.0
Name: livepandas
Version: 0.1.7
Summary: Give a little life to your data.
Home-page: http://www.livepandas.com/package
Author: Jorge E. Cardona
Author-email: jorge@cardona.co
License: PSF
Platform: UNKNOWN
